uv/__init__.py
uv/__main__.py
uv/_find_uv.py
uv/py.typed
uv-0.9.28.data/scripts/uv
uv-0.9.28.data/scripts/uvx
uv-0.9.28.dist-info/METADATA
uv-0.9.28.dist-info/WHEEL
uv-0.9.28.dist-info/licenses/LICENSE-APACHE
uv-0.9.28.dist-info/licenses/LICENSE-MIT
uv-0.9.28.dist-info/RECORD
