Metadata-Version: 2.4
Name: uv
Version: 0.9.28
Classifier: Development Status :: 5 - Production/Stable
Classifier: Environment :: Console
Classifier: Intended Audience :: Developers
Classifier: Operating System :: OS Independent
Classifier: License :: OSI Approved :: MIT License
Classifier: License :: OSI Approved :: Apache Software License
Classifier: Programming Language :: Python
Classifier: Programming Language :: Python :: 3.8
Classifier: Programming Language :: Python :: 3.9
Classifier: Programming Language :: Python :: 3.10
Classifier: Programming Language :: Python :: 3.11
Classifier: Programming Language :: Python :: 3.12
Classifier: Programming Language :: Python :: 3.13
Classifier: Programming Language :: Python :: 3.14
Classifier: Programming Language :: Python :: 3.15
Classifier: Programming Language :: Python :: 3 :: Only
Classifier: Programming Language :: Rust
Classifier: Topic :: Software Development :: Quality Assurance
Classifier: Topic :: Software Development :: Testing
Classifier: Topic :: Software Development :: Libraries
License-File: LICENSE-APACHE
License-File: LICENSE-MIT
Summary: An extremely fast Python package and project manager, written in Rust.
Keywords: uv,requirements,packaging
Home-Page: https://pypi.org/project/uv/
Author-email: "Astral Software Inc." <hey@astral.sh>
Requires-Python: >=3.8
Project-URL: Changelog, https://github.com/astral-sh/uv/blob/main/CHANGELOG.md
Project-URL: Discord, https://discord.gg/astral-sh
Project-URL: Documentation, https://docs.astral.sh/uv
Project-URL: Releases, https://github.com/astral-sh/uv/releases
Project-URL: Repository, https://github.com/astral-sh/uv
